gastli-1.0.1.dist-info/METADATA
gastli-1.0.1.dist-info/WHEEL
gastli-1.0.1.dist-info/LICENSE
gastli/dimensions.cpython-310-darwin.so
gastli/constants.cpython-310-darwin.so
gastli/fortinput.cpython-310-darwin.so
gastli/fortspec.cpython-310-darwin.so
gastli/gastli_interior.cpython-310-darwin.so
gastli/GASTLI.py
gastli/Guillot10.py
gastli/radius_hse.py
gastli/atm_models_interp.py
gastli/Coupling.py
gastli/Thermal_evolution.py
gastli/water_curves.py
gastli-1.0.1.dist-info/RECORD
