Metadata-Version: 2.1
Name: gastli
Version: 1.0.1
Summary: The GAS gianT modeL for Interiors
Author-Email: Lorena Acuna <acuna@mpia.de>
License: BSD 3-Clause License
Requires-Dist: numpy>=1.25.0
Requires-Dist: pandas>=2.0.3
Requires-Dist: scipy>=1.11.1
Requires-Dist: h5py>=3.10.0
Requires-Dist: matplotlib>=3.7.2
Requires-Dist: pytest>=8.2.2
